{
  "db_name": "PostgreSQL",
  "query": "\n            UPDATE tasker_tasks_dlq\n            SET resolution_status = COALESCE($2::text::dlq_resolution_status, resolution_status),\n                resolution_timestamp = CASE WHEN $2 IS NOT NULL THEN NOW() ELSE resolution_timestamp END,\n                resolution_notes = COALESCE($3, resolution_notes),\n                resolved_by = COALESCE($4, resolved_by),\n                metadata = COALESCE($5, metadata),\n                updated_at = NOW()\n            WHERE dlq_entry_uuid = $1\n            ",
  "describe": {
    "columns": [],
    "parameters": {
      "Left": [
        "Uuid",
        "Text",
        "Text",
        "Varchar",
        "Jsonb"
      ]
    },
    "nullable": []
  },
  "hash": "63f6f91e310b540d704e95cdf61df45d2b2d0741e9075ef9a5e8184f1d08bb43"
}
