{
  "db_name": "PostgreSQL",
  "query": "\n            SELECT COUNT(*) as count\n            FROM tasker_workflow_steps ws\n            LEFT JOIN (\n                SELECT DISTINCT ON (workflow_step_uuid) workflow_step_uuid, to_state\n                FROM tasker_workflow_step_transitions\n                WHERE most_recent = true\n                ORDER BY workflow_step_uuid, sort_key DESC\n            ) current_states ON current_states.workflow_step_uuid = ws.workflow_step_uuid\n            WHERE ws.task_uuid = $1::uuid\n              AND (current_states.to_state IS NULL\n                   OR current_states.to_state NOT IN ('complete', 'resolved_manually'))\n            ",
  "describe": {
    "columns": [
      {
        "ordinal": 0,
        "name": "count",
        "type_info": "Int8"
      }
    ],
    "parameters": {
      "Left": [
        "Uuid"
      ]
    },
    "nullable": [
      null
    ]
  },
  "hash": "125a1e249cfee51e9cf3342badff7b7bbb272d2c231c0daf873d203f6d043fa4"
}
