{
  "db_name": "PostgreSQL",
  "query": "\n        INSERT INTO tasker_named_tasks (\n            named_task_uuid,\n            task_namespace_uuid,\n            name,\n            version,\n            configuration,\n            created_at,\n            updated_at\n        )\n        VALUES ($1, $2, $3, '1.0.0', $4, NOW(), NOW())\n        ON CONFLICT (named_task_uuid) DO NOTHING\n        ",
  "describe": {
    "columns": [],
    "parameters": {
      "Left": [
        "Uuid",
        "Uuid",
        "Varchar",
        "Jsonb"
      ]
    },
    "nullable": []
  },
  "hash": "1cfe319c10682bcea3a4fb7eea334800d43c30e2b209de913f8bfd00bed030e8"
}
